voipbox_plugin/__init__.py
voipbox_plugin/choices.py
voipbox_plugin/filters.py
voipbox_plugin/forms.py
voipbox_plugin/models.py
voipbox_plugin/navigation.py
voipbox_plugin/tables.py
voipbox_plugin/urls.py
voipbox_plugin/views.py
voipbox_plugin/api/__init__.py
voipbox_plugin/api/serializers.py
voipbox_plugin/api/urls.py
voipbox_plugin/api/views.py
voipbox_plugin/migrations/0001_initial.py
voipbox_plugin/migrations/__init__.py
voipbox_plugin/templates/voipbox_plugin/pool.html
voipbox_plugin/templates/voipbox_plugin/pool_list.html
voipbox_plugin/templates/voipbox_plugin/voicecircuit.html
voipbox_plugin-0.0.6.dist-info/licenses/LICENSE
voipbox_plugin-0.0.6.dist-info/METADATA
voipbox_plugin-0.0.6.dist-info/WHEEL
voipbox_plugin-0.0.6.dist-info/top_level.txt
voipbox_plugin-0.0.6.dist-info/RECORD
