Metadata-Version: 2.4
Name: voipbox-plugin
Version: 0.0.6
License: MIT License
Project-URL: Documentation, https://github.com/panaceya/voipbox_plugin/blob/main/README.md
Project-URL: Source, https://github.com/panaceya/voipbox_plugin/
Project-URL: Tracker, https://github.com/panaceya/voipbox_plugin/issues
Keywords: netbox,netbox-plugin,voipbox
Classifier: Development Status :: 4 - Beta
Classifier: Programming Language :: Python :: 3
Classifier: Programming Language :: Python :: 3.6
Classifier: Programming Language :: Python :: 3.7
Classifier: Programming Language :: Python :: 3.8
Requires-Python: >=3.10.0
License-File: LICENSE
Dynamic: license-file
